fossil_director/__init__.py
fossil_director/server.py
fossil_director-1.0.dist-info/METADATA
fossil_director-1.0.dist-info/WHEEL
fossil_director-1.0.dist-info/entry_points.txt
fossil_director-1.0.dist-info/top_level.txt
fossil_director-1.0.dist-info/zip-safe
fossil_director-1.0.dist-info/RECORD
