Metadata-Version: 2.1
Name: fossil_director
Version: 1.0
Summary: fossil director
Home-page: https://code.pobblelabs.org/fossil/fossil_director
Author: Dave St.Germain
Author-email: dave@st.germa.in
License: BSD 3-Clause License
Keywords: protocol
Classifier: License :: OSI Approved :: BSD License
Classifier: Programming Language :: Python :: 3
Classifier: Programming Language :: Python :: 3.8
Classifier: Programming Language :: Python :: 3.9
Classifier: Programming Language :: Python :: 3.10
Classifier: Programming Language :: Python :: 3.11
Classifier: Programming Language :: Python :: 3.12
Classifier: Development Status :: 4 - Beta
Classifier: Environment :: Console
Classifier: Intended Audience :: System Administrators
Classifier: Intended Audience :: Developers
Classifier: Operating System :: OS Independent
Classifier: Topic :: Software Development :: Version Control
Classifier: Topic :: System :: Archiving
Requires-Python: >=3.8
